README.md
setup.cfg
setup.py
qcat/__init__.py
qcat/adapters.py
qcat/calibration.py
qcat/cli.py
qcat/config.py
qcat/eval.py
qcat/eval_full.py
qcat/eval_roc.py
qcat/layout.py
qcat/scanner.py
qcat/scanner_base.py
qcat/scanner_brill.py
qcat/scanner_dual.py
qcat/scanner_epi2me.py
qcat/scanner_guppy.py
qcat/scanner_simple.py
qcat/utils.py
qcat.egg-info/PKG-INFO
qcat.egg-info/SOURCES.txt
qcat.egg-info/dependency_links.txt
qcat.egg-info/entry_points.txt
qcat.egg-info/requires.txt
qcat.egg-info/top_level.txt
qcat/resources/kits/DUAL_3p.yml
qcat/resources/kits/DUAL_5p.yml
qcat/resources/kits/NBD104_3p.yml
qcat/resources/kits/NBD104_5p.yml
qcat/resources/kits/NBD104_NBD114_3p.yml
qcat/resources/kits/NBD104_NBD114_5p.yml
qcat/resources/kits/NBD114_3p.yml
qcat/resources/kits/NBD114_5p.yml
qcat/resources/kits/PBC001_3p.yml
qcat/resources/kits/PBC001_5p.yml
qcat/resources/kits/PBC096_3p.yml
qcat/resources/kits/PBC096_5p.yml
qcat/resources/kits/PBK004_LWB001_3p.yml
qcat/resources/kits/PBK004_LWB001_5p.yml
qcat/resources/kits/RAB201_3p.yml
qcat/resources/kits/RAB201_5p_a.yml
qcat/resources/kits/RAB201_5p_c.yml
qcat/resources/kits/RBK001.yml
qcat/resources/kits/RBK004.yml
qcat/resources/kits/RPB004_RLB001.yml
qcat/resources/kits/VMK001.yml
qcat/resources/kits/simple_extended.yml
qcat/resources/kits/simple_standard.yml