Metadata-Version: 2.1
Name: qcat
Version: 1.0.1
Summary: Qcat is Python command-line tool for demultiplexing Oxford Nanopore reads from FASTQ files
Home-page: https://github.com/nanoporetech/qcat/
Author: Oxford Nanopore Technologies Ltd.
Author-email: philipp.rescheneder@nanoporetech.com
License: Mozilla Public License Version 2.0
Platform: UNKNOWN
Provides-Extra: DOCS
